Sack/__init__.py
Christmas_Gifts-0.0.1.dist-info/LICENSE
Christmas_Gifts-0.0.1.dist-info/METADATA
Christmas_Gifts-0.0.1.dist-info/WHEEL
Christmas_Gifts-0.0.1.dist-info/top_level.txt
Christmas_Gifts-0.0.1.dist-info/RECORD
