Metadata-Version: 2.1
Name: Christmas-Gifts
Version: 0.0.1
Summary: A PACKAGE FOR EVERYTHING IN PYTHON
Home-page: UNKNOWN
Author: Shanthosh aka Santa
Author-email: santasandy1702@gmail.com
License: UNKNOWN
Platform: UNKNOWN
License-File: LICENSE
